{
    "latitude": 53.783043,
    "longitude": 20.486542,
    "generationtime_ms": 0.3802776336669922,
    "utc_offset_seconds": 3600,
    "timezone": "Europe/Berlin",
    "timezone_abbreviation": "GMT+1",
    "elevation": 143.0,
    "current_units": {
        "time": "iso8601",
        "interval": "seconds",
        "temperature_2m": "\u00b0C",
        "relative_humidity_2m": "%",
        "apparent_temperature": "\u00b0C",
        "is_day": "",
        "precipitation": "mm",
        "weather_code": "wmo code",
        "cloud_cover": "%",
        "pressure_msl": "hPa",
        "surface_pressure": "hPa",
        "wind_speed_10m": "km/h"
    },
    "current": {
        "time": "2026-02-17T20:45",
        "interval": 900,
        "temperature_2m": -6.8,
        "relative_humidity_2m": 87,
        "apparent_temperature": -11.4,
        "is_day": 0,
        "precipitation": 0.0,
        "weather_code": 3,
        "cloud_cover": 100,
        "pressure_msl": 1009.0,
        "surface_pressure": 990.7,
        "wind_speed_10m": 9.7
    },
    "hourly_units": {
        "time": "iso8601",
        "temperature_2m": "\u00b0C",
        "relative_humidity_2m": "%",
        "dew_point_2m": "\u00b0C",
        "precipitation_probability": "%",
        "precipitation": "mm",
        "weather_code": "wmo code",
        "pressure_msl": "hPa",
        "surface_pressure": "hPa",
        "wind_speed_10m": "km/h",
        "cloud_cover": "%"
    },
    "hourly": {
        "time": [
            "2026-02-17T00:00",
            "2026-02-17T01:00",
            "2026-02-17T02:00",
            "2026-02-17T03:00",
            "2026-02-17T04:00",
            "2026-02-17T05:00",
            "2026-02-17T06:00",
            "2026-02-17T07:00",
            "2026-02-17T08:00",
            "2026-02-17T09:00",
            "2026-02-17T10:00",
            "2026-02-17T11:00",
            "2026-02-17T12:00",
            "2026-02-17T13:00",
            "2026-02-17T14:00",
            "2026-02-17T15:00",
            "2026-02-17T16:00",
            "2026-02-17T17:00",
            "2026-02-17T18:00",
            "2026-02-17T19:00",
            "2026-02-17T20:00",
            "2026-02-17T21:00",
            "2026-02-17T22:00",
            "2026-02-17T23:00",
            "2026-02-18T00:00",
            "2026-02-18T01:00",
            "2026-02-18T02:00",
            "2026-02-18T03:00",
            "2026-02-18T04:00",
            "2026-02-18T05:00",
            "2026-02-18T06:00",
            "2026-02-18T07:00",
            "2026-02-18T08:00",
            "2026-02-18T09:00",
            "2026-02-18T10:00",
            "2026-02-18T11:00",
            "2026-02-18T12:00",
            "2026-02-18T13:00",
            "2026-02-18T14:00",
            "2026-02-18T15:00",
            "2026-02-18T16:00",
            "2026-02-18T17:00",
            "2026-02-18T18:00",
            "2026-02-18T19:00",
            "2026-02-18T20:00",
            "2026-02-18T21:00",
            "2026-02-18T22:00",
            "2026-02-18T23:00",
            "2026-02-19T00:00",
            "2026-02-19T01:00",
            "2026-02-19T02:00",
            "2026-02-19T03:00",
            "2026-02-19T04:00",
            "2026-02-19T05:00",
            "2026-02-19T06:00",
            "2026-02-19T07:00",
            "2026-02-19T08:00",
            "2026-02-19T09:00",
            "2026-02-19T10:00",
            "2026-02-19T11:00",
            "2026-02-19T12:00",
            "2026-02-19T13:00",
            "2026-02-19T14:00",
            "2026-02-19T15:00",
            "2026-02-19T16:00",
            "2026-02-19T17:00",
            "2026-02-19T18:00",
            "2026-02-19T19:00",
            "2026-02-19T20:00",
            "2026-02-19T21:00",
            "2026-02-19T22:00",
            "2026-02-19T23:00",
            "2026-02-20T00:00",
            "2026-02-20T01:00",
            "2026-02-20T02:00",
            "2026-02-20T03:00",
            "2026-02-20T04:00",
            "2026-02-20T05:00",
            "2026-02-20T06:00",
            "2026-02-20T07:00",
            "2026-02-20T08:00",
            "2026-02-20T09:00",
            "2026-02-20T10:00",
            "2026-02-20T11:00",
            "2026-02-20T12:00",
            "2026-02-20T13:00",
            "2026-02-20T14:00",
            "2026-02-20T15:00",
            "2026-02-20T16:00",
            "2026-02-20T17:00",
            "2026-02-20T18:00",
            "2026-02-20T19:00",
            "2026-02-20T20:00",
            "2026-02-20T21:00",
            "2026-02-20T22:00",
            "2026-02-20T23:00",
            "2026-02-21T00:00",
            "2026-02-21T01:00",
            "2026-02-21T02:00",
            "2026-02-21T03:00",
            "2026-02-21T04:00",
            "2026-02-21T05:00",
            "2026-02-21T06:00",
            "2026-02-21T07:00",
            "2026-02-21T08:00",
            "2026-02-21T09:00",
            "2026-02-21T10:00",
            "2026-02-21T11:00",
            "2026-02-21T12:00",
            "2026-02-21T13:00",
            "2026-02-21T14:00",
            "2026-02-21T15:00",
            "2026-02-21T16:00",
            "2026-02-21T17:00",
            "2026-02-21T18:00",
            "2026-02-21T19:00",
            "2026-02-21T20:00",
            "2026-02-21T21:00",
            "2026-02-21T22:00",
            "2026-02-21T23:00",
            "2026-02-22T00:00",
            "2026-02-22T01:00",
            "2026-02-22T02:00",
            "2026-02-22T03:00",
            "2026-02-22T04:00",
            "2026-02-22T05:00",
            "2026-02-22T06:00",
            "2026-02-22T07:00",
            "2026-02-22T08:00",
            "2026-02-22T09:00",
            "2026-02-22T10:00",
            "2026-02-22T11:00",
            "2026-02-22T12:00",
            "2026-02-22T13:00",
            "2026-02-22T14:00",
            "2026-02-22T15:00",
            "2026-02-22T16:00",
            "2026-02-22T17:00",
            "2026-02-22T18:00",
            "2026-02-22T19:00",
            "2026-02-22T20:00",
            "2026-02-22T21:00",
            "2026-02-22T22:00",
            "2026-02-22T23:00",
            "2026-02-23T00:00",
            "2026-02-23T01:00",
            "2026-02-23T02:00",
            "2026-02-23T03:00",
            "2026-02-23T04:00",
            "2026-02-23T05:00",
            "2026-02-23T06:00",
            "2026-02-23T07:00",
            "2026-02-23T08:00",
            "2026-02-23T09:00",
            "2026-02-23T10:00",
            "2026-02-23T11:00",
            "2026-02-23T12:00",
            "2026-02-23T13:00",
            "2026-02-23T14:00",
            "2026-02-23T15:00",
            "2026-02-23T16:00",
            "2026-02-23T17:00",
            "2026-02-23T18:00",
            "2026-02-23T19:00",
            "2026-02-23T20:00",
            "2026-02-23T21:00",
            "2026-02-23T22:00",
            "2026-02-23T23:00"
        ],
        "temperature_2m": [
            -10.3,
            -10.3,
            -10.3,
            -10.3,
            -10.2,
            -10.3,
            -10.4,
            -10.6,
            -10.3,
            -9.8,
            -8.9,
            -8.6,
            -8.1,
            -7.7,
            -7.2,
            -6.6,
            -6.6,
            -6.6,
            -6.9,
            -6.9,
            -6.9,
            -6.8,
            -6.8,
            -6.8,
            -6.8,
            -6.8,
            -6.7,
            -6.7,
            -6.6,
            -6.5,
            -6.3,
            -6.1,
            -6.3,
            -6.1,
            -5.4,
            -4.5,
            -3.9,
            -3.8,
            -3.7,
            -3.4,
            -3.7,
            -4.6,
            -5.6,
            -5.8,
            -6.4,
            -6.5,
            -6.2,
            -6.5,
            -7.0,
            -7.6,
            -8.0,
            -8.3,
            -8.4,
            -8.9,
            -9.0,
            -9.0,
            -8.0,
            -6.8,
            -5.2,
            -3.8,
            -2.3,
            -1.8,
            -1.5,
            -1.5,
            -2.1,
            -2.6,
            -3.2,
            -3.7,
            -5.0,
            -5.8,
            -6.5,
            -7.4,
            -7.9,
            -6.9,
            -6.2,
            -5.3,
            -4.7,
            -4.8,
            -5.2,
            -5.2,
            -4.8,
            -4.1,
            -3.5,
            -3.0,
            -2.4,
            -2.0,
            -2.0,
            -2.1,
            -2.3,
            -5.1,
            -6.2,
            -6.6,
            -7.2,
            -7.8,
            -7.9,
            -8.3,
            -8.6,
            -8.9,
            -9.1,
            -9.0,
            -8.8,
            -8.8,
            -8.5,
            -8.1,
            -7.3,
            -6.4,
            -5.5,
            -4.6,
            -3.7,
            -3.0,
            -2.5,
            -2.2,
            -1.9,
            -1.3,
            -0.6,
            0.0,
            0.3,
            0.6,
            0.7,
            0.7,
            0.6,
            0.4,
            0.2,
            -0.1,
            -0.2,
            0.0,
            0.4,
            0.9,
            1.4,
            2.0,
            2.5,
            2.8,
            3.0,
            3.0,
            2.8,
            2.5,
            2.2,
            2.0,
            1.7,
            1.6,
            1.9,
            2.3,
            2.7,
            3.0,
            3.3,
            3.5,
            3.5,
            3.3,
            3.2,
            3.0,
            2.8,
            2.7,
            2.8,
            3.0,
            3.2,
            3.2,
            3.3,
            3.3,
            3.3,
            3.2,
            3.0,
            2.8,
            2.7,
            2.5,
            2.5,
            2.5,
            2.5,
            2.5
        ],
        "relative_humidity_2m": [
            62,
            63,
            65,
            68,
            69,
            69,
            69,
            70,
            71,
            74,
            75,
            82,
            80,
            78,
            77,
            77,
            81,
            83,
            85,
            87,
            87,
            87,
            87,
            87,
            88,
            88,
            88,
            89,
            89,
            90,
            89,
            89,
            86,
            83,
            79,
            72,
            72,
            75,
            71,
            65,
            64,
            72,
            79,
            81,
            85,
            90,
            90,
            86,
            82,
            82,
            84,
            85,
            86,
            87,
            85,
            83,
            81,
            78,
            71,
            66,
            60,
            59,
            60,
            67,
            75,
            80,
            86,
            86,
            89,
            86,
            86,
            86,
            89,
            89,
            88,
            87,
            87,
            86,
            87,
            86,
            83,
            72,
            68,
            68,
            69,
            70,
            73,
            74,
            76,
            86,
            86,
            88,
            89,
            89,
            89,
            89,
            89,
            87,
            87,
            87,
            86,
            84,
            83,
            81,
            79,
            76,
            74,
            71,
            69,
            68,
            71,
            76,
            80,
            82,
            82,
            83,
            85,
            87,
            89,
            92,
            94,
            96,
            97,
            97,
            98,
            98,
            98,
            98,
            96,
            94,
            92,
            91,
            90,
            90,
            91,
            92,
            94,
            94,
            95,
            95,
            96,
            96,
            97,
            96,
            96,
            95,
            94,
            93,
            92,
            93,
            94,
            95,
            95,
            93,
            92,
            93,
            92,
            92,
            92,
            93,
            94,
            96,
            97,
            97,
            98,
            98,
            98,
            98
        ],
        "dew_point_2m": [
            -16.2,
            -16.0,
            -15.6,
            -15.1,
            -14.8,
            -14.9,
            -15.0,
            -15.0,
            -14.5,
            -13.5,
            -12.5,
            -11.1,
            -10.9,
            -10.9,
            -10.5,
            -9.9,
            -9.3,
            -9.0,
            -9.0,
            -8.7,
            -8.7,
            -8.6,
            -8.6,
            -8.6,
            -8.4,
            -8.4,
            -8.4,
            -8.2,
            -8.1,
            -7.9,
            -7.8,
            -7.6,
            -8.3,
            -8.5,
            -8.5,
            -8.8,
            -8.2,
            -7.5,
            -8.2,
            -9.1,
            -9.5,
            -8.8,
            -8.7,
            -8.5,
            -8.5,
            -7.8,
            -7.6,
            -8.4,
            -9.6,
            -10.1,
            -10.2,
            -10.3,
            -10.3,
            -10.6,
            -11.0,
            -11.3,
            -10.7,
            -10.0,
            -9.7,
            -9.2,
            -9.0,
            -8.7,
            -8.2,
            -6.8,
            -6.0,
            -5.6,
            -5.2,
            -5.7,
            -6.5,
            -7.7,
            -8.5,
            -9.3,
            -9.4,
            -8.4,
            -7.8,
            -7.1,
            -6.6,
            -6.8,
            -7.1,
            -7.2,
            -7.2,
            -8.4,
            -8.5,
            -8.1,
            -7.3,
            -6.7,
            -6.2,
            -6.1,
            -6.1,
            -7.1,
            -8.1,
            -8.2,
            -8.6,
            -9.2,
            -9.5,
            -9.8,
            -10.2,
            -10.6,
            -10.9,
            -10.8,
            -10.8,
            -10.9,
            -10.9,
            -10.7,
            -10.4,
            -9.9,
            -9.4,
            -9.1,
            -8.6,
            -8.1,
            -7.1,
            -5.9,
            -4.9,
            -4.1,
            -3.2,
            -2.5,
            -1.9,
            -1.3,
            -0.9,
            -0.5,
            -0.2,
            -0.1,
            -0.2,
            -0.4,
            -0.5,
            -0.2,
            0.2,
            0.5,
            0.8,
            1.0,
            1.2,
            1.4,
            1.5,
            1.5,
            1.5,
            1.4,
            1.3,
            1.1,
            0.9,
            0.9,
            1.3,
            1.8,
            2.2,
            2.5,
            2.7,
            2.7,
            2.5,
            2.2,
            2.0,
            2.0,
            2.0,
            2.0,
            2.0,
            2.0,
            2.1,
            2.1,
            2.2,
            2.2,
            2.2,
            2.2,
            2.2,
            2.2,
            2.2,
            2.2,
            2.2,
            2.2,
            2.2,
            2.2
        ],
        "precipitation_probability": [
            0,
            0,
            0,
            0,
            0,
            0,
            0,
            0,
            0,
            1,
            6,
            17,
            32,
            47,
            62,
            77,
            82,
            71,
            50,
            35,
            31,
            32,
            33,
            32,
            31,
            27,
            19,
            8,
            0,
            0,
            0,
            0,
            0,
            0,
            0,
            0,
            0,
            0,
            0,
            0,
            0,
            0,
            0,
            0,
            0,
            0,
            0,
            0,
            0,
            0,
            0,
            0,
            0,
            0,
            0,
            0,
            1,
            1,
            2,
            2,
            2,
            2,
            4,
            7,
            8,
            7,
            6,
            4,
            3,
            1,
            0,
            0,
            0,
            0,
            1,
            2,
            2,
            2,
            1,
            0,
            0,
            0,
            0,
            0,
            0,
            0,
            0,
            0,
            0,
            0,
            0,
            0,
            0,
            0,
            0,
            0,
            0,
            0,
            0,
            0,
            0,
            0,
            0,
            0,
            0,
            0,
            0,
            0,
            0,
            0,
            3,
            8,
            12,
            16,
            21,
            24,
            26,
            27,
            29,
            33,
            37,
            39,
            38,
            36,
            33,
            30,
            28,
            25,
            22,
            19,
            18,
            18,
            20,
            22,
            24,
            26,
            29,
            32,
            36,
            39,
            40,
            41,
            43,
            48,
            53,
            57,
            57,
            55,
            53,
            52,
            52,
            53,
            55,
            58,
            59,
            58,
            57,
            55,
            54,
            53,
            52,
            51,
            50,
            49,
            49,
            48,
            48,
            47
        ],
        "precipitation": [
            0.0,
            0.0,
            0.0,
            0.0,
            0.0,
            0.0,
            0.0,
            0.0,
            0.0,
            0.0,
            0.1,
            0.3,
            0.3,
            0.2,
            0.1,
            0.1,
            0.1,
            0.1,
            0.1,
            0.1,
            0.1,
            0.1,
            0.1,
            0.1,
            0.0,
            0.1,
            0.1,
            0.0,
            0.0,
            0.0,
            0.0,
            0.0,
            0.0,
            0.0,
            0.0,
            0.0,
            0.0,
            0.0,
            0.0,
            0.0,
            0.0,
            0.0,
            0.0,
            0.0,
            0.0,
            0.0,
            0.0,
            0.0,
            0.0,
            0.0,
            0.0,
            0.0,
            0.0,
            0.0,
            0.0,
            0.0,
            0.0,
            0.0,
            0.0,
            0.0,
            0.0,
            0.0,
            0.0,
            0.0,
            0.0,
            0.0,
            0.0,
            0.0,
            0.0,
            0.0,
            0.0,
            0.0,
            0.0,
            0.0,
            0.0,
            0.0,
            0.0,
            0.0,
            0.0,
            0.0,
            0.0,
            0.0,
            0.0,
            0.0,
            0.0,
            0.0,
            0.0,
            0.0,
            0.0,
            0.0,
            0.0,
            0.0,
            0.0,
            0.0,
            0.0,
            0.0,
            0.0,
            0.0,
            0.0,
            0.0,
            0.0,
            0.0,
            0.0,
            0.0,
            0.0,
            0.0,
            0.0,
            0.0,
            0.0,
            0.0,
            0.1,
            0.1,
            0.1,
            0.0,
            0.0,
            0.0,
            0.1,
            0.1,
            0.1,
            0.3,
            0.3,
            0.3,
            0.1,
            0.1,
            0.1,
            0.0,
            0.0,
            0.0,
            0.0,
            0.0,
            0.0,
            0.0,
            0.0,
            0.0,
            0.0,
            0.0,
            0.0,
            1.1,
            1.1,
            1.1,
            0.5,
            0.5,
            0.5,
            0.2,
            0.2,
            0.2,
            0.0,
            0.0,
            0.0,
            0.0,
            0.0,
            0.0,
            0.0,
            0.0,
            0.0,
            0.0,
            0.0,
            0.0,
            0.0,
            0.0,
            0.0,
            0.0,
            0.0,
            0.0,
            0.3,
            0.3,
            0.3,
            0.3
        ],
        "weather_code": [
            3,
            3,
            3,
            3,
            3,
            3,
            3,
            3,
            3,
            3,
            71,
            71,
            71,
            71,
            71,
            71,
            51,
            71,
            71,
            71,
            71,
            71,
            71,
            51,
            3,
            71,
            51,
            3,
            3,
            3,
            3,
            3,
            3,
            3,
            3,
            3,
            3,
            3,
            2,
            0,
            0,
            0,
            0,
            0,
            0,
            1,
            1,
            0,
            0,
            0,
            0,
            0,
            0,
            0,
            0,
            0,
            3,
            1,
            0,
            0,
            0,
            0,
            0,
            0,
            3,
            3,
            3,
            1,
            2,
            0,
            0,
            0,
            0,
            0,
            2,
            3,
            3,
            3,
            3,
            3,
            2,
            1,
            3,
            2,
            3,
            3,
            3,
            3,
            3,
            3,
            3,
            3,
            3,
            1,
            0,
            0,
            2,
            3,
            3,
            3,
            3,
            3,
            3,
            3,
            3,
            3,
            3,
            3,
            3,
            3,
            71,
            71,
            71,
            3,
            3,
            3,
            51,
            51,
            51,
            73,
            73,
            73,
            71,
            71,
            71,
            3,
            3,
            3,
            3,
            3,
            3,
            3,
            3,
            3,
            3,
            3,
            3,
            71,
            71,
            71,
            53,
            53,
            53,
            51,
            51,
            51,
            3,
            3,
            3,
            3,
            3,
            3,
            3,
            3,
            3,
            3,
            3,
            3,
            3,
            3,
            3,
            3,
            3,
            3,
            51,
            51,
            51,
            51
        ],
        "pressure_msl": [
            1007.4,
            1007.1,
            1006.9,
            1006.3,
            1006.1,
            1006.1,
            1006.4,
            1006.5,
            1007.4,
            1007.2,
            1007.3,
            1008.1,
            1007.8,
            1007.8,
            1007.8,
            1008.1,
            1007.9,
            1008.3,
            1008.9,
            1008.7,
            1008.8,
            1009.0,
            1009.2,
            1009.2,
            1009.2,
            1009.2,
            1009.1,
            1008.9,
            1009.0,
            1009.1,
            1009.2,
            1009.5,
            1009.8,
            1010.1,
            1010.2,
            1010.6,
            1010.5,
            1010.4,
            1010.6,
            1010.7,
            1011.0,
            1011.4,
            1011.4,
            1011.5,
            1011.8,
            1011.8,
            1012.0,
            1012.1,
            1012.0,
            1012.0,
            1011.6,
            1011.0,
            1010.9,
            1010.9,
            1010.9,
            1011.2,
            1011.3,
            1011.1,
            1010.8,
            1010.7,
            1010.6,
            1010.7,
            1010.7,
            1010.8,
            1011.3,
            1011.7,
            1012.1,
            1012.8,
            1013.1,
            1013.9,
            1015.1,
            1015.7,
            1016.1,
            1017.4,
            1018.5,
            1019.6,
            1021.1,
            1022.0,
            1022.8,
            1023.5,
            1024.5,
            1025.2,
            1026.0,
            1026.7,
            1027.1,
            1027.3,
            1027.7,
            1027.7,
            1027.7,
            1027.7,
            1028.1,
            1028.5,
            1028.4,
            1028.7,
            1028.5,
            1027.8,
            1027.4,
            1026.9,
            1026.5,
            1025.9,
            1025.0,
            1024.6,
            1023.7,
            1023.2,
            1022.3,
            1021.3,
            1020.2,
            1019.1,
            1017.9,
            1016.7,
            1015.5,
            1014.4,
            1013.4,
            1012.5,
            1011.7,
            1011.1,
            1010.6,
            1010.2,
            1009.9,
            1009.8,
            1009.8,
            1009.8,
            1009.9,
            1010.1,
            1010.2,
            1010.2,
            1010.1,
            1010.1,
            1010.2,
            1010.4,
            1010.5,
            1010.4,
            1010.2,
            1010.0,
            1009.7,
            1009.4,
            1009.0,
            1008.5,
            1007.9,
            1007.3,
            1006.6,
            1005.9,
            1005.4,
            1005.2,
            1005.2,
            1005.3,
            1005.5,
            1005.7,
            1005.9,
            1006.0,
            1006.0,
            1006.0,
            1005.9,
            1005.9,
            1005.8,
            1005.8,
            1005.8,
            1005.9,
            1006.1,
            1006.4,
            1006.8,
            1007.2,
            1007.5,
            1007.7,
            1007.8,
            1007.7,
            1007.6,
            1007.4
        ],
        "surface_pressure": [
            988.9,
            988.6,
            988.4,
            987.8,
            987.6,
            987.6,
            987.9,
            988.0,
            988.9,
            988.7,
            988.9,
            989.7,
            989.4,
            989.5,
            989.5,
            989.8,
            989.6,
            990.0,
            990.6,
            990.4,
            990.5,
            990.7,
            990.9,
            990.9,
            990.9,
            990.9,
            990.8,
            990.6,
            990.7,
            990.8,
            990.9,
            991.2,
            991.5,
            991.8,
            992.0,
            992.4,
            992.4,
            992.3,
            992.5,
            992.6,
            992.9,
            993.2,
            993.1,
            993.2,
            993.5,
            993.5,
            993.7,
            993.8,
            993.6,
            993.6,
            993.2,
            992.6,
            992.4,
            992.4,
            992.4,
            992.7,
            992.9,
            992.8,
            992.6,
            992.6,
            992.6,
            992.7,
            992.7,
            992.8,
            993.3,
            993.6,
            994.0,
            994.6,
            994.8,
            995.6,
            996.7,
            997.2,
            997.6,
            998.9,
            1000.1,
            1001.2,
            1002.7,
            1003.6,
            1004.4,
            1005.0,
            1006.0,
            1006.8,
            1007.6,
            1008.3,
            1008.8,
            1009.0,
            1009.4,
            1009.4,
            1009.4,
            1009.2,
            1009.5,
            1009.9,
            1009.7,
            1010.0,
            1009.8,
            1009.0,
            1008.6,
            1008.1,
            1007.7,
            1007.1,
            1006.3,
            1005.9,
            1005.0,
            1004.5,
            1003.7,
            1002.8,
            1001.8,
            1000.8,
            999.6,
            998.5,
            997.4,
            996.3,
            995.3,
            994.5,
            993.8,
            993.2,
            992.7,
            992.4,
            992.1,
            992.0,
            992.0,
            992.0,
            992.0,
            992.2,
            992.3,
            992.3,
            992.3,
            992.3,
            992.4,
            992.6,
            992.8,
            992.7,
            992.5,
            992.3,
            992.0,
            991.7,
            991.3,
            990.8,
            990.2,
            989.6,
            988.9,
            988.2,
            987.8,
            987.6,
            987.6,
            987.7,
            987.9,
            988.1,
            988.3,
            988.4,
            988.4,
            988.4,
            988.3,
            988.3,
            988.2,
            988.2,
            988.2,
            988.3,
            988.5,
            988.8,
            989.2,
            989.6,
            989.8,
            990.0,
            990.1,
            990.0,
            989.9,
            989.7
        ],
        "wind_speed_10m": [
            12.2,
            11.5,
            13.0,
            13.3,
            14.0,
            14.4,
            14.4,
            14.8,
            15.5,
            16.2,
            14.0,
            13.3,
            13.3,
            14.0,
            14.0,
            15.1,
            11.9,
            11.2,
            11.2,
            10.8,
            9.0,
            10.1,
            9.4,
            10.1,
            9.0,
            9.4,
            8.3,
            8.3,
            7.6,
            6.8,
            6.8,
            7.6,
            7.2,
            5.4,
            6.1,
            7.2,
            8.6,
            10.8,
            10.1,
            8.3,
            9.4,
            8.6,
            9.7,
            9.7,
            9.4,
            8.6,
            8.3,
            8.3,
            9.0,
            9.0,
            8.6,
            8.6,
            8.3,
            9.0,
            9.0,
            10.8,
            10.1,
            8.6,
            8.6,
            9.7,
            11.5,
            12.6,
            11.2,
            10.1,
            9.7,
            9.4,
            11.9,
            10.1,
            9.7,
            9.0,
            7.9,
            9.4,
            8.3,
            6.5,
            9.6,
            11.4,
            13.2,
            13.1,
            11.0,
            9.5,
            9.6,
            11.1,
            11.1,
            10.3,
            10.8,
            12.5,
            11.2,
            9.5,
            6.2,
            5.7,
            10.3,
            10.7,
            11.2,
            12.2,
            12.5,
            14.0,
            14.3,
            15.0,
            16.1,
            16.7,
            17.5,
            17.7,
            20.0,
            21.7,
            20.5,
            18.7,
            17.8,
            18.1,
            19.1,
            20.1,
            20.5,
            20.9,
            21.1,
            20.6,
            19.5,
            18.2,
            16.5,
            14.7,
            13.0,
            11.6,
            10.5,
            9.5,
            9.3,
            9.8,
            10.9,
            11.4,
            11.8,
            12.1,
            12.3,
            12.6,
            13.0,
            14.3,
            16.1,
            17.1,
            16.5,
            15.3,
            13.9,
            12.1,
            10.9,
            10.6,
            11.0,
            13.4,
            16.3,
            18.6,
            20.6,
            22.1,
            22.7,
            22.5,
            22.0,
            21.1,
            19.8,
            18.9,
            18.8,
            19.3,
            19.6,
            19.3,
            19.3,
            18.9,
            18.3,
            17.4,
            16.2,
            15.1,
            14.2,
            13.5,
            13.0,
            12.6,
            12.8,
            13.4
        ],
        "cloud_cover": [
            100,
            100,
            100,
            100,
            100,
            100,
            100,
            98,
            99,
            95,
            100,
            100,
            100,
            100,
            98,
            100,
            100,
            100,
            100,
            100,
            100,
            100,
            100,
            100,
            100,
            100,
            100,
            100,
            100,
            100,
            100,
            100,
            91,
            89,
            86,
            100,
            100,
            100,
            69,
            0,
            0,
            6,
            7,
            8,
            14,
            34,
            40,
            13,
            0,
            0,
            0,
            2,
            8,
            6,
            0,
            9,
            83,
            28,
            0,
            0,
            0,
            4,
            2,
            6,
            100,
            100,
            100,
            22,
            70,
            0,
            0,
            0,
            0,
            38,
            82,
            100,
            100,
            98,
            100,
            91,
            66,
            41,
            97,
            77,
            98,
            99,
            100,
            98,
            98,
            100,
            100,
            100,
            95,
            30,
            13,
            0,
            51,
            100,
            88,
            91,
            99,
            93,
            100,
            100,
            100,
            100,
            100,
            100,
            100,
            100,
            100,
            100,
            100,
            100,
            100,
            100,
            100,
            100,
            100,
            100,
            100,
            100,
            100,
            100,
            100,
            100,
            100,
            100,
            100,
            100,
            100,
            100,
            100,
            100,
            100,
            100,
            100,
            100,
            100,
            100,
            100,
            100,
            100,
            100,
            100,
            100,
            100,
            100,
            100,
            100,
            100,
            100,
            100,
            100,
            100,
            100,
            100,
            100,
            100,
            100,
            100,
            100,
            100,
            100,
            100,
            100,
            100,
            100
        ]
    },
    "location_id": 763166
}